full_sub.v

module full_sub(
    input A, B, Bin,
    output D, Bout
);

assign D    = A ^ B ^ Bin;
assign Bout = (~A & B) | (~A & Bin) | (B & Bin);

endmodule

full_sub_tb.v
module full_sub_tb;

reg A, B, Bin;
wire D, Bout;

full_sub uut (
    .A(A),
    .B(B),
    .Bin(Bin),
    .D(D),
    .Bout(Bout)
);

initial begin
    $dumpfile("full_sub_tb.vcd");
    $dumpvars(0, full_sub_tb);
end

initial begin
    A=0; B=0; Bin=0;
    #10 A=0; B=0; Bin=1;
    #10 A=0; B=1; Bin=0;
    #10 A=0; B=1; Bin=1;
    #10 A=1; B=0; Bin=0;
    #10 A=1; B=0; Bin=1;
    #10 A=1; B=1; Bin=0;
    #10 A=1; B=1; Bin=1;
    #10 $finish;
end

endmodule

full_sub_tb.vcd
$date
	Fri Jan 16 09:40:30 2026
$end
$version
	Icarus Verilog
$end
$timescale
	1s
$end
$scope module full_sub_tb $end
$var wire 1 ! D $end
$var wire 1 " Bout $end
$var reg 1 # A $end
$var reg 1 $ B $end
$var reg 1 % Bin $end
$scope module uut $end
$var wire 1 # A $end
$var wire 1 $ B $end
$var wire 1 % Bin $end
$var wire 1 " Bout $end
$var wire 1 ! D $end
$upscope $end
$upscope $end
$enddefinitions $end
$comment Show the parameter values. $end
$dumpall
$end
#0
$dumpvars
0%
0$
0#
0"
0!
$end
#10
1"
1!
1%
#20
0%
1$
#30
0!
1%
#40
0"
1!
0%
0$
1#
#50
0!
1%
#60
0%
1$
#70
1"
1!
1%
